perlreq/__init__.py
perlreq/__main__.py
perlreq-1.dist-info/METADATA
perlreq-1.dist-info/WHEEL
perlreq-1.dist-info/top_level.txt
perlreq-1.dist-info/RECORD
